{
    "etag": "W/\"6dc5c178b7907c37b900bc7c293366c954f77f73529e73aa5d86571916205317\"",
    "modified": "",
    "last_entry_id": "",
    "https://www.dicio.com.br/apaziguar/": true,
    "https://www.dicio.com.br/estrambotico/": true,
    "https://www.dicio.com.br/esnobe/": true,
    "https://www.dicio.com.br/enigmatico/": true,
    "https://www.dicio.com.br/encrenqueiro/": true,
    "https://www.dicio.com.br/embuste/": true,
    "https://www.dicio.com.br/empafia/": true,
    "https://www.dicio.com.br/empenho/": true,
    "https://www.dicio.com.br/encalacrar/": true,
    "https://www.dicio.com.br/enfadonho/": true,
    "https://www.dicio.com.br/ensimesmado/": true,
    "https://www.dicio.com.br/congracar/": true,
    "https://www.dicio.com.br/estranho/": true,
    "https://www.dicio.com.br/exabundante/": true,
    "https://www.dicio.com.br/exorbitante/": true,
    "https://www.dicio.com.br/exultante/": true,
    "https://www.dicio.com.br/fajuto/": true,
    "https://www.dicio.com.br/fantasmagorico/": true,
    "https://www.dicio.com.br/abobada/": true,
    "https://www.dicio.com.br/flacido/": true,
    "https://www.dicio.com.br/forrobodo/": true,
    "https://www.dicio.com.br/balela/": true,
    "https://www.dicio.com.br/fugaz/": true,
    "https://www.dicio.com.br/galhofar/": true,
    "https://www.dicio.com.br/galopear/": true,
    "https://www.dicio.com.br/garboso/": true,
    "https://www.dicio.com.br/gargalhar/": true,
    "https://www.dicio.com.br/garrancho/": true,
    "https://www.dicio.com.br/chumbrega/": true,
    "https://www.dicio.com.br/glutao/": true,
    "https://www.dicio.com.br/grugulejar/": true,
    "https://www.dicio.com.br/heterodoxo/": true,
    "https://www.dicio.com.br/iconoclasta/": true,
    "https://www.dicio.com.br/ignominia/": true,
    "https://www.dicio.com.br/imbroglio/": true,
    "https://www.dicio.com.br/corso/": true,
    "https://www.dicio.com.br/premencia/": true,
    "https://www.dicio.com.br/ineficaz/": true,
    "https://www.dicio.com.br/inelutavel/": true,
    "https://www.dicio.com.br/inexaurivel/": true,
    "https://www.dicio.com.br/infortunio/": true,
    "https://www.dicio.com.br/ininteligivel/": true,
    "https://www.dicio.com.br/insolito/": true,
    "https://www.dicio.com.br/javardo/": true,
    "https://www.dicio.com.br/lambao/": true,
    "https://www.dicio.com.br/lamentavel/": true,
    "https://www.dicio.com.br/leviandade/": true,
    "https://www.dicio.com.br/lisonja/": true,
    "https://www.dicio.com.br/macabro/": true,
    "https://www.dicio.com.br/macambuzio/": true,
    "https://www.dicio.com.br/maleavel/": true,
    "https://www.dicio.com.br/hierofania/": true,
    "https://www.dicio.com.br/minguante/": true,
    "https://www.dicio.com.br/moribundo/": true,
    "https://www.dicio.com.br/nefasto/": true,
    "https://www.dicio.com.br/nostalgico/": true,
    "https://www.dicio.com.br/alquimista/": true,
    "https://www.dicio.com.br/anacronico/": true,
    "https://www.dicio.com.br/apocalipse/": true,
    "https://www.dicio.com.br/arabesco/": true,
    "https://www.dicio.com.br/desmantelado/": true,
    "https://www.dicio.com.br/bucolico/": true,
    "https://www.dicio.com.br/imiscuir/": true,
    "https://www.dicio.com.br/caleidoscopio/": true,
    "https://www.dicio.com.br/candido/": true,
    "https://www.dicio.com.br/casmurro/": true,
    "https://www.dicio.com.br/caudaloso/": true,
    "https://www.dicio.com.br/physique-du-role/": true,
    "https://www.dicio.com.br/cetaceo/": true,
    "https://www.dicio.com.br/ciclope/": true,
    "https://www.dicio.com.br/coloquio/": true,
    "https://www.dicio.com.br/compendioso/": true,
    "https://www.dicio.com.br/concomitante/": true,
    "https://www.dicio.com.br/criptico/": true,
    "https://www.dicio.com.br/deploravel/": true,
    "https://www.dicio.com.br/desprovido/": true,
    "https://www.dicio.com.br/devaneio/": true,
    "https://www.dicio.com.br/dileto/": true,
    "https://www.dicio.com.br/dissecacao/": true,
    "https://www.dicio.com.br/dodecaedro/": true,
    "https://www.dicio.com.br/ecossistema/": true,
    "https://www.dicio.com.br/ectoplasma/": true,
    "https://www.dicio.com.br/efemero/": true,
    "https://www.dicio.com.br/elocucao/": true,
    "https://www.dicio.com.br/embaraco/": true,
    "https://www.dicio.com.br/fidelissimo/": true,
    "https://www.dicio.com.br/enlevo/": true,
    "https://www.dicio.com.br/birosca/": true,
    "https://www.dicio.com.br/equivoco/": true,
    "https://www.dicio.com.br/exotico/": true,
    "https://www.dicio.com.br/falacia/": true,
    "https://www.dicio.com.br/fulgido/": true,
    "https://www.dicio.com.br/fulgurante/": true,
    "https://www.dicio.com.br/galaxia/": true,
    "https://www.dicio.com.br/galvanizar/": true,
    "https://www.dicio.com.br/genuino/": true,
    "https://www.dicio.com.br/hibernal/": true,
    "https://www.dicio.com.br/chinfrim/": true,
    "https://www.dicio.com.br/iconico/": true,
    "https://www.dicio.com.br/idiossincrasia/": true,
    "https://www.dicio.com.br/a-excecao-de/": true,
    "https://www.dicio.com.br/hipercorrecao/": true,
    "https://www.dicio.com.br/solitude/": true,
    "https://www.dicio.com.br/intermitente/": true,
    "https://www.dicio.com.br/jactancia/": true,
    "https://www.dicio.com.br/kafkiano/": true,
    "https://www.dicio.com.br/labirinto/": true,
    "https://www.dicio.com.br/luminoso/": true,
    "https://www.dicio.com.br/magnanimo/": true,
    "https://www.dicio.com.br/majestoso/": true,
    "https://www.dicio.com.br/malabarismo/": true,
    "https://www.dicio.com.br/malevolo/": true,
    "https://www.dicio.com.br/melancolia/": true,
    "https://www.dicio.com.br/metamorfose/": true,
    "https://www.dicio.com.br/monotono/": true,
    "https://www.dicio.com.br/mitigacao/": true,
    "https://www.dicio.com.br/sommelier/": true,
    "https://www.dicio.com.br/nebuloso/": true,
    "https://www.dicio.com.br/nefelibata/": true,
    "https://www.dicio.com.br/nirvana/": true,
    "https://www.dicio.com.br/nostalgia/": true,
    "https://www.dicio.com.br/oasis/": true,
    "https://www.dicio.com.br/obscuridade/": true,
    "https://www.dicio.com.br/obsoleto/": true,
    "https://www.dicio.com.br/onix/": true,
    "https://www.dicio.com.br/oraculo/": true,
    "https://www.dicio.com.br/paradoxo/": true,
    "https://www.dicio.com.br/perene/": true,
    "https://www.dicio.com.br/perspicaz/": true,
    "https://www.dicio.com.br/plenitude/": true,
    "https://www.dicio.com.br/polifonico/": true,
    "https://www.dicio.com.br/pomposo/": true,
    "https://www.dicio.com.br/precipicio/": true,
    "https://www.dicio.com.br/profusao/": true,
    "https://www.dicio.com.br/borocoxo/": true,
    "https://www.dicio.com.br/quica/": true,
    "https://www.dicio.com.br/reticente/": true,
    "https://www.dicio.com.br/reverbero/": true,
    "https://www.dicio.com.br/sarcasmo/": true,
    "https://www.dicio.com.br/serenidade/": true,
    "https://www.dicio.com.br/silogismo/": true,
    "https://www.dicio.com.br/suntuoso/": true,
    "https://www.dicio.com.br/supimpa/": true,
    "https://www.dicio.com.br/taciturno/": true,
    "https://www.dicio.com.br/tenaz/": true,
    "https://www.dicio.com.br/trivialidade/": true,
    "https://www.dicio.com.br/ubiquo/": true,
    "https://www.dicio.com.br/ululante/": true,
    "https://www.dicio.com.br/unissono/": true,
    "https://www.dicio.com.br/utopico/": true,
    "https://www.dicio.com.br/vanilina/": true,
    "https://www.dicio.com.br/verossimil/": true,
    "https://www.dicio.com.br/zenite-2/": true,
    "https://www.dicio.com.br/alquimia/": true,
    "https://www.dicio.com.br/anticristo/": true,
    "https://www.dicio.com.br/apoteose/": true,
    "https://www.dicio.com.br/arquipelago/": true,
    "https://www.dicio.com.br/ataraxia/": true,
    "https://www.dicio.com.br/basilica/": true,
    "https://www.dicio.com.br/bibelo/": true,
    "https://www.dicio.com.br/cacofonia/": true,
    "https://www.dicio.com.br/cacofonizar/": true,
    "https://www.dicio.com.br/cafundo/": true,
    "https://www.dicio.com.br/categorico/": true,
    "https://www.dicio.com.br/cenico/": true,
    "https://www.dicio.com.br/circunspecto/": true,
    "https://www.dicio.com.br/coalescencia/": true,
    "https://www.dicio.com.br/interface/": true,
    "https://www.dicio.com.br/dantesco/": true,
    "https://www.dicio.com.br/designio/": true,
    "https://www.dicio.com.br/dicotomia/": true,
    "https://www.dicio.com.br/efervescencia/": true,
    "https://www.dicio.com.br/elucubracao/": true,
    "https://www.dicio.com.br/chi-coracao/": true,
    "https://www.dicio.com.br/empirico/": true,
    "https://www.dicio.com.br/enigma/": true,
    "https://www.dicio.com.br/ensandecer/": true,
    "https://www.dicio.com.br/epicurismo/": true,
    "https://www.dicio.com.br/escarlate/": true,
    "https://www.dicio.com.br/esdruxulo/": true,
    "https://www.dicio.com.br/estratagema/": true,
    "https://www.dicio.com.br/exilio/": true,
    "https://www.dicio.com.br/extravagante/": true,
    "https://www.dicio.com.br/falaz/": true,
    "https://www.dicio.com.br/fenix/": true,
    "https://www.dicio.com.br/fulminante/": true,
    "https://www.dicio.com.br/galanteio/": true,
    "https://www.dicio.com.br/genuflexao/": true,
    "https://www.dicio.com.br/hibridismo/": true,
    "https://www.dicio.com.br/hieroglifo/": true,
    "https://www.dicio.com.br/hipnotico/": true,
    "https://www.dicio.com.br/incolume/": true,
    "https://www.dicio.com.br/inebriante/": true,
    "https://www.dicio.com.br/infinito/": true,
    "https://www.dicio.com.br/inospito/": true,
    "https://www.dicio.com.br/invejavel/": true,
    "https://www.dicio.com.br/languido/": true,
    "https://www.dicio.com.br/ludico/": true,
    "https://www.dicio.com.br/magnitude/": true,
    "https://www.dicio.com.br/malabarista/": true,
    "https://www.dicio.com.br/matriosca/": true,
    "https://www.dicio.com.br/mistico/": true,
    "https://www.dicio.com.br/onirico/": true,
    "https://www.dicio.com.br/rutilo/": true,
    "https://www.dicio.com.br/eflorescencia/": true,
    "https://www.dicio.com.br/efigie/": true,
    "https://www.dicio.com.br/obnubilar/": true,
    "https://www.dicio.com.br/plebeu/": true,
    "https://www.dicio.com.br/esperanca/": true,
    "https://www.dicio.com.br/exaltado/": true,
    "https://www.dicio.com.br/confins/": true,
    "https://www.dicio.com.br/perseveranca/": true,
    "https://www.dicio.com.br/vigorar/": true,
    "https://www.dicio.com.br/diabetes/": true,
    "https://www.dicio.com.br/imprescindivel/": true,
    "https://www.dicio.com.br/prenha/": true,
    "https://www.dicio.com.br/desvanecedor/": true,
    "https://www.dicio.com.br/receptar/": true,
    "https://www.dicio.com.br/adocao/": true,
    "https://www.dicio.com.br/manjolao/": true,
    "https://www.dicio.com.br/relutante/": true,
    "https://www.dicio.com.br/adictivo/": true,
    "https://www.dicio.com.br/ataude/": true,
    "https://www.dicio.com.br/inerente/": true,
    "https://www.dicio.com.br/grata/": true,
    "https://www.dicio.com.br/expressivo/": true,
    "https://www.dicio.com.br/dicionario/": true,
    "https://www.dicio.com.br/respeito/": true,
    "https://www.dicio.com.br/misura/": true,
    "https://www.dicio.com.br/peculiar/": true,
    "https://www.dicio.com.br/perspectiva/": true,
    "https://www.dicio.com.br/comunidade/": true,
    "https://www.dicio.com.br/rio/": true,
    "https://www.dicio.com.br/astucia/": true,
    "https://www.dicio.com.br/angra/": true,
    "https://www.dicio.com.br/acato-2/": true,
    "https://www.dicio.com.br/solicitude/": true,
    "https://www.dicio.com.br/denegrir/": true,
    "https://www.dicio.com.br/resiliencia/": true,
    "https://www.dicio.com.br/harmonioso/": true,
    "https://www.dicio.com.br/singular/": true,
    "https://www.dicio.com.br/repositor/": true,
    "https://www.dicio.com.br/condescendente/": true,
    "https://www.dicio.com.br/regozijar/": true,
    "https://www.dicio.com.br/conjuge/": true,
    "https://www.dicio.com.br/reciproco/": true,
    "https://www.dicio.com.br/asseio/": true,
    "https://www.dicio.com.br/excecao/": true,
    "https://www.dicio.com.br/intrinseco/": true,
    "https://www.dicio.com.br/clarao/": true,
    "https://www.dicio.com.br/pretensao/": true,
    "https://www.dicio.com.br/romance/": true,
    "https://www.dicio.com.br/vivido-2/": true,
    "https://www.dicio.com.br/reciprocidade/": true,
    "https://www.dicio.com.br/brigue/": true,
    "https://www.dicio.com.br/libras/": true,
    "https://www.dicio.com.br/de-repente/": true,
    "https://www.dicio.com.br/tripulante/": true,
    "https://www.dicio.com.br/franquiar/": true,
    "https://www.dicio.com.br/atracao-2/": true,
    "https://www.dicio.com.br/alvissaras/": true,
    "https://www.dicio.com.br/prescindir/": true,
    "https://www.dicio.com.br/transcricao/": true,
    "https://www.dicio.com.br/presuncoso/": true,
    "https://www.dicio.com.br/triceps/": true,
    "https://www.dicio.com.br/barco/": true,
    "https://www.dicio.com.br/plugar/": true,
    "https://www.dicio.com.br/protecionista/": true,
    "https://www.dicio.com.br/serendipidade/": true,
    "https://www.dicio.com.br/carater/": true,
    "https://www.dicio.com.br/exceto/": true,
    "https://www.dicio.com.br/bem-aventuranca/": true,
    "https://www.dicio.com.br/geolocalizacao/": true,
    "https://www.dicio.com.br/diligencia/": true,
    "https://www.dicio.com.br/enrodilha/": true,
    "https://www.dicio.com.br/dublar/": true,
    "https://www.dicio.com.br/infungivel/": true,
    "https://www.dicio.com.br/foge/": true,
    "https://www.dicio.com.br/gladiar/": true,
    "https://www.dicio.com.br/contrastivo/": true,
    "https://www.dicio.com.br/surpreender/": true,
    "https://www.dicio.com.br/cinico/": true,
    "https://www.dicio.com.br/arregimentado/": true,
    "https://www.dicio.com.br/intra-arterial/": true,
    "https://www.dicio.com.br/concessao/": true,
    "https://www.dicio.com.br/perturbacao/": true,
    "https://www.dicio.com.br/anuencia/": true,
    "https://www.dicio.com.br/reviravolta/": true,
    "https://www.dicio.com.br/art-deco/": true,
    "https://www.dicio.com.br/empestar/": true,
    "https://www.dicio.com.br/aviar/": true,
    "53b757d3fc5b10befd5eca895d62cdde": true,
    "b53b5e5fd1e2e227e871c7d5dc9fddf3": true,
    "163c4df1435748377b099d562173faaa": true,
    "e354f1fe5907c98e0ece35b03d2c6912": true,
    "9398b5530a54247a187b1312f141b216": true,
    "382fba89b777981510c2d1ef977a84b5": true,
    "61da35e71a8512d954069110eac256c6": true,
    "fe6f45fc86270f2c0220dd5277792d68": true,
    "e56488cc466190ff59e58297e469394d": true,
    "4ec18f2d1fcab0ac7ad6bc04bb19a7cb": true,
    "84e2c55c9818f95daaf3fb5fde202085": true,
    "dfc0b56f5de4e76d2f51184b0292291f": true,
    "processed_entries": [
        "4ec18f2d1fcab0ac7ad6bc04bb19a7cb",
        "84e2c55c9818f95daaf3fb5fde202085",
        "dfc0b56f5de4e76d2f51184b0292291f",
        "6583b5ef78bb8a045fde16b943ec54ad",
        "626d98714b355e8fa28b816a9f973730",
        "8f36272320855752151e6b5ada7f990a",
        "6558f8fa05d32ec88b6f5d626d043fe1",
        "25622bc3be96618eac847ae9f7afb83c",
        "55dbd7c4777d54ee0c70d810edfc3872",
        "d40f5b4d71ce0125a86e5d6e24e8c563",
        "815e4ced7ec0f905a24d7965ccb4f2b7",
        "47996b58afe3675b2f798ae47a366e52",
        "dc9ea9da8f71dea1873041c865864d1c",
        "bf5e7da9760b15118541711b3eecea67",
        "3f9337c2145cbc90bd81bbdffc7652bd",
        "7e1d998f620bafa37be8c1fc22e84203",
        "b3e00c68e0809b5d61ce618f0942cd5e",
        "a7c23bf42cce70ed5e60fba9a779b618",
        "2178a9a30ae7c89bf4f35b17470efde2",
        "ba08094ffd7df4e3ab99d02e3de22d09",
        "f44df06a2ee25c4840599962a6326529",
        "0ce3880bf3fa67bb09603487a4385feb",
        "5dbaf517e5114840f617441ae73936e0",
        "fecfb2bc9192e10c0cf942d054b16e1d",
        "3cb43c78f9849c57f3ea993e3eac03eb",
        "a02428065f6101b8ac7220a357306e18",
        "1d325dfad307d691c6389734a1473b1d",
        "0a5b240605fb93ce8c071489b2d3af40",
        "ae08c07ef49b0254e46d924be856bde7",
        "7c767a6bd1ebe285174cddbc984e5fad",
        "180430f7f6ecbe89f731b12416a6ad34",
        "83b85a2c4d663cc4d967ca2ec9aeb952",
        "bf4bf28a246ebdc632315c964b342550",
        "10fffc3e4833d69e5fda2056347014cc",
        "ebe634277f32c46e49f1b39fa754e4bc",
        "c11f1dd694d241de608b6985a005c5a5",
        "ab7e70aa64fbfa258b3e59790ee37c3e",
        "3d1940df1b89715a6d6c19b93a880245",
        "ac053931d2f5dd09d46d5c85a79bcdc7",
        "2de11d6f135a28cbfa99c3640f30cd15",
        "f3fbba6335369127be5de47e58a52459",
        "b4d48d0b13fa8b87c2347c27619b8020",
        "d7987c0eafe36232df85b3b962d1245f",
        "1a14b49d5c67df6eb96a3be87be61bd7",
        "7189478530f272face5eab0f0ed56fc1",
        "86eeb98047dd3d38c757c6c4058f6fb5",
        "d429026522b2091ed940e5833387be5c",
        "1811b3a5c2648b6ba90f5ea1e1adb0a9",
        "669c32722f72106f1dd7b9ad52794f32",
        "1d726347e4848e48a1de80d696c9a45d",
        "31569666e344c4c82c37d5d4987cd65d",
        "05b7ca1919b9ad8430e65d906ddc9127",
        "8a8b2f638a7d8c9b928841d9b8b86595",
        "8050e5873b4aa575faaaf75393b7fba4",
        "be58fddf360f25ae337b3587c47d297f",
        "5df1a910cda86d7f721b092d52fc0455",
        "f00bcc3c88fab53eab0eedf5cec7e795",
        "50a6a2c6f22365326efbcd2fd1019764",
        "8287680c22c11288e1b556cd25da3372",
        "5e2f04b734cfe92465eb8d13a9a341ec",
        "bc5e2423e567389f750a4b8509c15d29",
        "afe7f814f16eb264bba317701e891e0c",
        "16036b50154fe0568166d5e7fe8eca7a",
        "ae87cbaaaff7f41cb14fc5779f0bd6b3",
        "13d87d67b300f98f4c1cc0a4cbf3b199",
        "b7a3aa65bf9d6c54fa55a502567fc558",
        "0bc8311e4601e9b58473fd97ad94bf1d",
        "640d0d2820c306ee7b22f9dad12305e3",
        "e8da14604208bd4005d4012273407f83",
        "925e53a84ec291170eecee2b47ce3ef0",
        "1fdb3dd045b56d569bf294f6fb44cf75",
        "5a614920c97f81ab23134f7d63f9f036",
        "fe29f8db59b3cc194f0b75ad475f0c08",
        "5fe17ed32478f631a2d5aaaaf77126f2",
        "717e4e1a0754dd28ef593f77dc6a5146",
        "0c09debe9c25588d6d52744a7fa49bb7",
        "6c1cc1dce17daa8bf98260e3d3f7dbc6",
        "3b29cf0e3f3c4fc82632d53821eda135",
        "4cb2fa9078ff24f1ffec5f76802a6652",
        "a391a166a1be85aacfbb6f57b1307378",
        "a90d8fb278c29f38a4b0cf0962308b43",
        "f7e85db7d63f444d4ac572db4bc6a2b6",
        "c1ec9d695ac645e261f4b550d1cca715",
        "0e03bcc19089e0a201c680fff945127a",
        "825b1c72276fd09c7bc58863a6b0eac3",
        "bfeb45fe5cf386db90cea512a3c2011a",
        "97140ae999213b75b154974399675e0e",
        "9c9ec83411aeba4e3535c1f4db186eaf",
        "cfe49dbf68666b813ff02f1dddd11d22",
        "359e1371ea3984b35900cf24fcf79dcb",
        "b877ea5c43cb0e1325101809d00602eb",
        "822110b90a06b25c8b6d014caa712541",
        "b88ddeb408c3a3782781a48273fc8298",
        "1c98fa12ed33d56a0ba6d1c351a3d2c1",
        "04675bb375495f615b95edc11f0698ca",
        "7a380ec9e9221901237e8245fc24c932",
        "1463c95bc64415fb1c942ad56ef25139",
        "7d83059c0d4eacfdbecad1e921a3fb2e",
        "9f85740e07082d4e588e5abdee660081",
        "d83d0abbb944e47a840455b3bc4a7b08",
        "976b9662324adef3f92315b786bb2619",
        "8ab3a4bb172b62d28d3280ffe137b15d",
        "8c8240a5dc0a8f300779ea184d340072",
        "22bed58aaa4901766047521f5499d37a",
        "a280d74b0b873c8daff7075c9af7853d",
        "5994793ea9c6d220f10f95fd84469ed4",
        "705361279d8eaf351c4a0df80a9a0fb4",
        "a61bef41a53d29e00407e0bfcb92b571",
        "18d1cb9a34a3304c2005aaeb178d98a8",
        "9d45e5713171dc49082a61802cb2b57b",
        "7213d609a3086ec29aaf92f7255216f8",
        "512a9b78e4c3027650e96fe2e1bc8321",
        "894d413e11e5ebdd110dce2b98b2ffa6",
        "46681236fd4a650373196140639d8f93",
        "8fe8777abae780430ee69dcbec1be9e4",
        "9c480b97bd7d0d45f79932c4eb5dd958",
        "ab7541272f6482191f2ce4e8ec8d267a",
        "6d04c4552a77bff9cc7a21229dbf1a4a",
        "f89ad51daed1caa1dd77a3246808113b",
        "d3325321624841c4f0d1f9369426d564",
        "1a3f9774d3c484871eeaee2243578aec",
        "350340827bd142d21afcb465e36d6637",
        "dd4a564ab6c5e52d57a32e9faa736c91",
        "abb59c50bc59c82ec66dab881dc49aea",
        "5fe99167326622dcacb0181c0c2d118f",
        "8482b192d84b02fabfc8884505017626",
        "8645e630c012969b0140431016ff455b",
        "5c17a95877cac03b2fd39b7e83dc026d",
        "b4efe6a9259ee5fadbdb9699551beea5",
        "84c671bd9ff91b9b3a4e156cb3444877",
        "a110dcee2b76405ac2893fd701096c0c",
        "85b0f532aa12907e1b905109bf7a9676",
        "f9b82a5ed7a15b86e25909bc3fd605cd",
        "da90faf82d80276ba6ae2c35852e51ab",
        "9cfcd372a51796b787b5c4118d34e6e5",
        "b5bee46381cba36b5029e8a5a2272242",
        "ddb5cde14287c6a1f5d7c3c4fef01cd1",
        "48a2fe259db36ab713d9ae60af5dae68",
        "e59a67e34f5bd855a0aa75c68b222508",
        "9265bcbf9586f3eb14b1c090ba1897d0",
        "b9c90ca2aad356f5c8737a05353963f9",
        "f3de7e9d1b729e1ed24321808e2e5934",
        "8b396df02b69042551876910ac637de1",
        "f20657035da4c917eaef94ccd025e9db",
        "ba30eb5d11573460ce04d131cd9d7f04",
        "7fd90fb9542322314a9021df61ee5df0",
        "52876110c7b44213e2e57e3b83a3ce36",
        "5a06c42904c907b4d5a40a006b3279ce",
        "bba00b2824d669f70266b63799bffa60"
    ]
}